Metadata-Version: 2.1
Name: pyCheckLib
Version: 0.0.5
Summary: Amongus
Home-page: https://pornhub.com
Author: Slezzzy
Author-email: slezzzysmail@gmail.com
License-File: LICENSE
